fmp_data/__init__.py
fmp_data/async_client.py
fmp_data/base.py
fmp_data/client.py
fmp_data/config.py
fmp_data/exceptions.py
fmp_data/helpers.py
fmp_data/logger.py
fmp_data/models.py
fmp_data/py.typed
fmp_data/rate_limit.py
fmp_data/schema.py
fmp_data/alternative/__init__.py
fmp_data/alternative/async_client.py
fmp_data/alternative/client.py
fmp_data/alternative/endpoints.py
fmp_data/alternative/mapping.py
fmp_data/alternative/models.py
fmp_data/alternative/schema.py
fmp_data/batch/__init__.py
fmp_data/batch/_csv_utils.py
fmp_data/batch/async_client.py
fmp_data/batch/client.py
fmp_data/batch/endpoints.py
fmp_data/batch/mapping.py
fmp_data/batch/models.py
fmp_data/company/__init__.py
fmp_data/company/async_client.py
fmp_data/company/client.py
fmp_data/company/endpoints.py
fmp_data/company/hints.py
fmp_data/company/mapping.py
fmp_data/company/models.py
fmp_data/company/schema.py
fmp_data/economics/__init__.py
fmp_data/economics/async_client.py
fmp_data/economics/client.py
fmp_data/economics/endpoints.py
fmp_data/economics/mapping.py
fmp_data/economics/models.py
fmp_data/economics/schema.py
fmp_data/fundamental/__init__.py
fmp_data/fundamental/async_client.py
fmp_data/fundamental/client.py
fmp_data/fundamental/endpoints.py
fmp_data/fundamental/mapping.py
fmp_data/fundamental/models.py
fmp_data/fundamental/schema.py
fmp_data/index/__init__.py
fmp_data/index/async_client.py
fmp_data/index/client.py
fmp_data/index/endpoints.py
fmp_data/index/mapping.py
fmp_data/index/models.py
fmp_data/institutional/__init__.py
fmp_data/institutional/async_client.py
fmp_data/institutional/client.py
fmp_data/institutional/endpoints.py
fmp_data/institutional/mapping.py
fmp_data/institutional/models.py
fmp_data/institutional/schema.py
fmp_data/intelligence/__init__.py
fmp_data/intelligence/async_client.py
fmp_data/intelligence/client.py
fmp_data/intelligence/endpoints.py
fmp_data/intelligence/mapping.py
fmp_data/intelligence/models.py
fmp_data/intelligence/schema.py
fmp_data-2.1.5.dist-info/METADATA
fmp_data-2.1.5.dist-info/WHEEL
fmp_data-2.1.5.dist-info/entry_points.txt
fmp_data-2.1.5.dist-info/licenses/LICENSE
fmp_data-2.1.5.dist-info/licenses/NOTICE
fmp_data-2.1.5.dist-info/RECORD
