Metadata-Version: 2.4
Name: fmp-data
Version: 2.1.5
Summary: Python client for the Financial Modeling Prep API
Project-URL: Homepage, https://github.com/MehdiZare/fmp-data
Project-URL: Repository, https://github.com/MehdiZare/fmp-data
Project-URL: Documentation, https://mehdizare.github.io/fmp-data/
Author-email: Mehdi Zare <mehdizare@users.noreply.github.com>
Maintainer-email: Mehdi Zare <mehdizare@users.noreply.github.com>
License: MIT
License-File: LICENSE
License-File: NOTICE
Keywords: api,financial,financial data,fmp,market-data,stock market,stocks
Classifier: Development Status :: 5 - Production/Stable
Classifier: Framework :: AsyncIO
Classifier: Intended Audience :: Developers
Classifier: Intended Audience :: Financial and Insurance Industry
Classifier: License :: OSI Approved :: MIT License
Classifier: Operating System :: OS Independent
Classifier: Programming Language :: Python :: 3
Classifier: Programming Language :: Python :: 3 :: Only
Classifier: Programming Language :: Python :: 3.10
Classifier: Programming Language :: Python :: 3.11
Classifier: Programming Language :: Python :: 3.12
Classifier: Programming Language :: Python :: 3.13
Classifier: Programming Language :: Python :: 3.14
Classifier: Topic :: Office/Business :: Financial
Classifier: Topic :: Software Development :: Libraries :: Python Modules
Requires-Python: <3.15,>=3.10
Requires-Dist: httpx>=0.28.1
Requires-Dist: pydantic>=2.12.5
Requires-Dist: tenacity>=9.1.2
Provides-Extra: dev
Requires-Dist: bandit[toml]>=1.9.3; extra == 'dev'
Requires-Dist: coverage>=7.13.1; extra == 'dev'
Requires-Dist: freezegun>=1.5.5; extra == 'dev'
Requires-Dist: mypy>=1.19.1; extra == 'dev'
Requires-Dist: nox>=2025.11.12; extra == 'dev'
Requires-Dist: pip-audit>=2.10.0; extra == 'dev'
Requires-Dist: pre-commit>=4.5.1; extra == 'dev'
Requires-Dist: pytest-asyncio>=1.3.0; extra == 'dev'
Requires-Dist: pytest-cov>=7.0.0; extra == 'dev'
Requires-Dist: pytest-mock>=3.15.1; extra == 'dev'
Requires-Dist: pytest-xdist>=3.6.1; extra == 'dev'
Requires-Dist: pytest>=9.0.2; extra == 'dev'
Requires-Dist: python-dotenv>=1.1.1; extra == 'dev'
Requires-Dist: responses>=0.25.8; extra == 'dev'
Requires-Dist: rich>=14.2.0; extra == 'dev'
Requires-Dist: ruff>=0.14.13; extra == 'dev'
Requires-Dist: twine>=6.2.0; extra == 'dev'
Requires-Dist: vcrpy>=8.1.1; extra == 'dev'
Provides-Extra: docs
Requires-Dist: mkdocs-material>=9.7.1; extra == 'docs'
Requires-Dist: mkdocs>=1.6.1; extra == 'docs'
Requires-Dist: mkdocstrings-python>=2.0.1; extra == 'docs'
Provides-Extra: langchain
Requires-Dist: faiss-cpu>=1.13.2; extra == 'langchain'
Requires-Dist: langchain-community>=0.4.1; extra == 'langchain'
Requires-Dist: langchain-core>=1.2.7; extra == 'langchain'
Requires-Dist: langchain-openai>=1.1.7; extra == 'langchain'
Requires-Dist: langgraph>=1.0.6; extra == 'langchain'
Requires-Dist: openai>=2.15.0; extra == 'langchain'
Requires-Dist: tiktoken>=0.12.0; extra == 'langchain'
Provides-Extra: mcp
Requires-Dist: mcp[cli]>=1.25.0; extra == 'mcp'
Requires-Dist: pyyaml>=6.0.3; extra == 'mcp'
